visage/__init__.py
visage/bisenet.py
visage/resnet.py
visage/visualize.py
visage/bounding_boxes/__init__.py
visage/bounding_boxes/face_boxes_v2.py
visage/landmark_detection/__init__.py
visage/landmark_detection/pipnet.py
visage/landmark_detection/pipnet_config.py
visage/modules/__init__.py
visage/modules/FaceBoxesV2/__init__.py
visage/modules/FaceBoxesV2/detector.py
visage/modules/FaceBoxesV2/faceboxes_detector.py
visage/modules/FaceBoxesV2/utils/__init__.py
visage/modules/FaceBoxesV2/utils/box_utils.py
visage/modules/FaceBoxesV2/utils/build.py
visage/modules/FaceBoxesV2/utils/config.py
visage/modules/FaceBoxesV2/utils/faceboxes.py
visage/modules/FaceBoxesV2/utils/nms_wrapper.py
visage/modules/FaceBoxesV2/utils/prior_box.py
visage/modules/FaceBoxesV2/utils/timer.py
visage/modules/FaceBoxesV2/utils/nms/__init__.py
visage/modules/FaceBoxesV2/utils/nms/cpu_nms.c
visage/modules/FaceBoxesV2/utils/nms/cpu_nms.pyx
visage/modules/FaceBoxesV2/utils/nms/gpu_nms.hpp
visage/modules/FaceBoxesV2/utils/nms/gpu_nms.pyx
visage/modules/FaceBoxesV2/utils/nms/nms_kernel.cu
visage/modules/FaceBoxesV2/utils/nms/py_cpu_nms.py
visage/modules/PIPNet/__init__.py
visage/modules/PIPNet/lib/__init__.py
visage/modules/PIPNet/lib/demo.py
visage/modules/PIPNet/lib/functions.py
visage/modules/PIPNet/lib/mobilenetv3.py
visage/modules/PIPNet/lib/networks.py
visage/modules/PIPNet/lib/preprocess.py
visage/modules/PIPNet/meanfaces/__init__.py
visage/modules/PIPNet/meanfaces/AFLW/__init__.py
visage/modules/PIPNet/meanfaces/AFLW/meanface.txt
visage/modules/PIPNet/meanfaces/COFW/__init__.py
visage/modules/PIPNet/meanfaces/COFW/meanface.txt
visage/modules/PIPNet/meanfaces/LaPa/__init__.py
visage/modules/PIPNet/meanfaces/LaPa/meanface.txt
visage/modules/PIPNet/meanfaces/WFLW/__init__.py
visage/modules/PIPNet/meanfaces/WFLW/meanface.txt
visage/modules/PIPNet/meanfaces/data_300W/__init__.py
visage/modules/PIPNet/meanfaces/data_300W/meanface.txt
visage/modules/PIPNet/meanfaces/data_300W_CELEBA/__init__.py
visage-0.2.2.dist-info/METADATA
visage-0.2.2.dist-info/WHEEL
visage-0.2.2.dist-info/top_level.txt
visage-0.2.2.dist-info/RECORD
