Metadata-Version: 2.1
Name: visage
Version: 0.2.2
Summary: Face Parsers
Home-page: https://github.com/tobias-kirschstein/face-parser
Author: Tobias Kirschstein
Author-email: tobias.kirschstein@gmail.com
Classifier: Programming Language :: Python :: 3
Classifier: Operating System :: OS Independent
Requires-Python: >=3.8
Requires-Dist: opencv-python
Requires-Dist: cython
Requires-Dist: requests
Requires-Dist: scipy
